Metadata-Version: 2.1
Name: tkpick
Version: 1.0.0
Summary: Get pixel color using the cursor
Home-page: https://github.com/beucismis/tkpick
Author: Adil Gurbuz
Author-email: beucismis@tutamail.com
License: GPL-3.0
Keywords: tkinter,pick,cursor,pixel,color
Platform: Linux
Classifier: Topic :: Utilities
Classifier: Natural Language :: English
Classifier: Topic :: Multimedia :: Graphics
Classifier: Environment :: X11 Applications
Classifier: Programming Language :: Python
Classifier: Programming Language :: Python :: 3.5
Classifier: Programming Language :: Python :: 3.6
Classifier: Programming Language :: Python :: 3.7
Classifier: Environment :: X11 Applications :: GTK
Requires-Python: >=3.5
